plotxel/__init__.py
plotxel/axes.py
plotxel/charts.py
plotxel/helpers.py
test/__init__.py
test/test_plotxel.py
plotxel-0.0.9.dist-info/LICENSE
plotxel-0.0.9.dist-info/METADATA
plotxel-0.0.9.dist-info/WHEEL
plotxel-0.0.9.dist-info/top_level.txt
plotxel-0.0.9.dist-info/RECORD
